metalpriceapi/__init__.py
metalpriceapi/client.py
metalpriceapi-1.1.2.dist-info/METADATA
metalpriceapi-1.1.2.dist-info/WHEEL
metalpriceapi-1.1.2.dist-info/top_level.txt
metalpriceapi-1.1.2.dist-info/RECORD
