Metadata-Version: 2.2
Name: metalpriceapi
Version: 1.1.2
Summary: Official Python wrapper for metalpriceapi.com
Home-page: https://github.com/metalpriceapi/metalpriceapi-python
Author: MetalpriceAPI
Author-email: contact@metalpriceapi.com
Keywords: currency,metal price,exchangerate,rates
Requires-Dist: requests>=2.31.0
Dynamic: author
Dynamic: author-email
Dynamic: description
Dynamic: description-content-type
Dynamic: home-page
Dynamic: keywords
Dynamic: requires-dist
Dynamic: summary
